LICENCE
MANIFEST.in
README
setup.py
libschwa_python.egg-info/PKG-INFO
libschwa_python.egg-info/SOURCES.txt
libschwa_python.egg-info/dependency_links.txt
libschwa_python.egg-info/requires.txt
libschwa_python.egg-info/top_level.txt
schwa/__init__.py
schwa/dr/__init__.py
schwa/dr/constants.py
schwa/dr/containers.py
schwa/dr/decoration.py
schwa/dr/decorators.py
schwa/dr/exceptions.py
schwa/dr/fields_core.py
schwa/dr/fields_extra.py
schwa/dr/meta.py
schwa/dr/reader.py
schwa/dr/rtklasses.py
schwa/dr/runtime.py
schwa/dr/schema.py
schwa/dr/writer.py
schwa/dr/contrib/__init__.py
schwa/dr/contrib/processing.py
schwa/dr/contrib/tokenizers/__init__.py
schwa/dr/contrib/tokenizers/text_tokenizer.py
schwa/dr/contrib/writers/__init__.py
schwa/dr/contrib/writers/column_writer.py
schwa/dr/contrib/writers/html_writer.py
schwa/dr/contrib/writers/writer.py
tokenizer/_python.h
tokenizer/callback_stream.cc
tokenizer/callback_stream.h
tokenizer/exception.h
tokenizer/module.cc
tokenizer/pystream.h
tokenizer/seq_stream.cc
tokenizer/seq_stream.h
tokenizer/text_stream.cc
tokenizer/text_stream.h